knarrow/__about__.py
knarrow/__init__.py
knarrow/angle_method.py
knarrow/angle_method.pyi
knarrow/c_method.py
knarrow/c_method.pyi
knarrow/distance_method.py
knarrow/distance_method.pyi
knarrow/kneedle.py
knarrow/kneedle.pyi
knarrow/main.py
knarrow/main.pyi
knarrow/menger.py
knarrow/menger.pyi
knarrow/ols.py
knarrow/ols.pyi
knarrow/py.typed
knarrow/util.py
knarrow/util.pyi
knarrow/cli/__init__.py
knarrow-0.8.1.dist-info/METADATA
knarrow-0.8.1.dist-info/WHEEL
knarrow-0.8.1.dist-info/entry_points.txt
knarrow-0.8.1.dist-info/licenses/LICENSE.txt
knarrow-0.8.1.dist-info/RECORD
