Metadata-Version: 2.4
Name: knarrow
Version: 0.8.1
Summary: Shoot a knarrow to the knee
Project-URL: Documentation, https://github.com/InCogNiTo124/knarrow#readme
Project-URL: Issues, https://github.com/InCogNiTo124/knarrow/issues
Project-URL: Source, https://github.com/InCogNiTo124/knarrow
Author-email: Marijan Smetko <msmetko@msmetko.xyz>
License-Expression: Apache-2.0
License-File: LICENSE.txt
Keywords: elbow,knee,kneedle,optimization
Classifier: Development Status :: 3 - Alpha
Classifier: Intended Audience :: Developers
Classifier: Intended Audience :: Information Technology
Classifier: Intended Audience :: Science/Research
Classifier: License :: OSI Approved :: Apache Software License
Classifier: Programming Language :: Python
Classifier: Programming Language :: Python :: 3
Classifier: Programming Language :: Python :: 3 :: Only
Classifier: Programming Language :: Python :: 3.10
Classifier: Programming Language :: Python :: 3.11
Classifier: Programming Language :: Python :: 3.12
Classifier: Programming Language :: Python :: 3.13
Classifier: Topic :: Scientific/Engineering :: Artificial Intelligence
Classifier: Topic :: Scientific/Engineering :: Information Analysis
Classifier: Topic :: Scientific/Engineering :: Mathematics
Classifier: Topic :: Utilities
Classifier: Typing :: Typed
Requires-Python: >=3.10
Requires-Dist: numpy
Provides-Extra: cli
Requires-Dist: typer==0.15.2; extra == 'cli'
